bob/__init__.py
bob/bio/__init__.py
bob/bio/spear/__init__.py
bob/bio/spear/audio_processing.py
bob/bio/spear/utils.py
bob/bio/spear/annotator/__init__.py
bob/bio/spear/annotator/energy_2gauss.py
bob/bio/spear/annotator/energy_thr.py
bob/bio/spear/annotator/mod_4hz.py
bob/bio/spear/config/__init__.py
bob/bio/spear/config/annotator/__init__.py
bob/bio/spear/config/annotator/energy_2gauss.py
bob/bio/spear/config/annotator/energy_thr.py
bob/bio/spear/config/annotator/mod_4hz.py
bob/bio/spear/config/database/__init__.py
bob/bio/spear/config/database/asvspoof.py
bob/bio/spear/config/database/avspoof.py
bob/bio/spear/config/database/mini_voxforge.py
bob/bio/spear/config/database/mobio_audio_female.py
bob/bio/spear/config/database/mobio_audio_male.py
bob/bio/spear/config/database/nist_sre04to16.py
bob/bio/spear/config/database/timit.py
bob/bio/spear/config/database/voicepa.py
bob/bio/spear/config/database/voxceleb.py
bob/bio/spear/config/database/voxforge.py
bob/bio/spear/config/extractor/__init__.py
bob/bio/spear/config/extractor/mfcc60.py
bob/bio/spear/config/pipeline/__init__.py
bob/bio/spear/config/pipeline/mfcc60_gmm_default.py
bob/bio/spear/config/pipeline/mfcc60_gmm_mini.py
bob/bio/spear/config/pipeline/mfcc60_gmm_mobio.py
bob/bio/spear/config/pipeline/mfcc60_isv_default.py
bob/bio/spear/config/pipeline/mfcc60_isv_mini.py
bob/bio/spear/config/pipeline/mfcc60_ivector.py
bob/bio/spear/config/pipeline/mfcc60_ivector_postprocess.py
bob/bio/spear/config/pipeline/speechbrain_ecapa_voxceleb.py
bob/bio/spear/config/preprocessor/mod_4hz.py
bob/bio/spear/database/__init__.py
bob/bio/spear/database/asvspoof.py
bob/bio/spear/database/asvspoof2017.py
bob/bio/spear/database/avspoof.py
bob/bio/spear/database/mobio.py
bob/bio/spear/database/nist_sre04to16.py
bob/bio/spear/database/timit.py
bob/bio/spear/database/utils.py
bob/bio/spear/database/voicepa.py
bob/bio/spear/database/voxceleb.py
bob/bio/spear/database/voxforge.py
bob/bio/spear/extractor/Cepstral.py
bob.bio.spear-5.0.1.dist-info/COPYING
bob.bio.spear-5.0.1.dist-info/METADATA
bob.bio.spear-5.0.1.dist-info/WHEEL
bob.bio.spear-5.0.1.dist-info/entry_points.txt
bob.bio.spear-5.0.1.dist-info/top_level.txt
bob.bio.spear-5.0.1.dist-info/RECORD
